LICENSE.txt
README.rst
setup.cfg
setup.py
drama/__init__.py
drama/restrictions.py
drama/restrictors.py
drama/utils.py
drama/wrapper.py
drama_wrapper.egg-info/PKG-INFO
drama_wrapper.egg-info/SOURCES.txt
drama_wrapper.egg-info/dependency_links.txt
drama_wrapper.egg-info/requires.txt
drama_wrapper.egg-info/top_level.txt